local_dm_control_suite/__init__.py
local_dm_control_suite/acrobot.py
local_dm_control_suite/ball_in_cup.py
local_dm_control_suite/base.py
local_dm_control_suite/cartpole.py
local_dm_control_suite/cheetah.py
local_dm_control_suite/explore.py
local_dm_control_suite/finger.py
local_dm_control_suite/fish.py
local_dm_control_suite/hopper.py
local_dm_control_suite/humanoid.py
local_dm_control_suite/humanoid_CMU.py
local_dm_control_suite/lqr.py
local_dm_control_suite/lqr_solver.py
local_dm_control_suite/manipulator.py
local_dm_control_suite/pendulum.py
local_dm_control_suite/point_mass.py
local_dm_control_suite/quadruped.py
local_dm_control_suite/reacher.py
local_dm_control_suite/stacker.py
local_dm_control_suite/swimmer.py
local_dm_control_suite/walker.py
local_dm_control_suite/common/__init__.py
local_dm_control_suite/utils/__init__.py
local_dm_control_suite/utils/parse_amc.py
local_dm_control_suite/utils/parse_amc_test.py
local_dm_control_suite/utils/randomizers.py
local_dm_control_suite/utils/randomizers_test.py
local_dm_control_suite/wrappers/__init__.py
local_dm_control_suite/wrappers/action_noise.py
local_dm_control_suite/wrappers/action_noise_test.py
local_dm_control_suite/wrappers/pixels.py
local_dm_control_suite/wrappers/pixels_test.py
mtenv/__init__.py
mtenv/core.py
mtenv/envs/__init__.py
mtenv/envs/registration.py
mtenv/envs/control/__init__.py
mtenv/envs/control/acrobot.py
mtenv/envs/control/cartpole.py
mtenv/envs/control/setup.py
mtenv/envs/hipbmdp/__init__.py
mtenv/envs/hipbmdp/dmc_env.py
mtenv/envs/hipbmdp/env.py
mtenv/envs/hipbmdp/setup.py
mtenv/envs/hipbmdp/wrappers/__init__.py
mtenv/envs/hipbmdp/wrappers/dmc_wrapper.py
mtenv/envs/hipbmdp/wrappers/framestack.py
mtenv/envs/hipbmdp/wrappers/sticky_observation.py
mtenv/envs/metaworld/__init__.py
mtenv/envs/metaworld/env.py
mtenv/envs/metaworld/setup.py
mtenv/envs/metaworld/wrappers/__init__.py
mtenv/envs/metaworld/wrappers/normalized_env.py
mtenv/envs/mpte/__init__.py
mtenv/envs/mpte/setup.py
mtenv-1.0.dist-info/LICENSE
mtenv-1.0.dist-info/METADATA
mtenv-1.0.dist-info/WHEEL
mtenv-1.0.dist-info/top_level.txt
mtenv-1.0.dist-info/RECORD
