Metadata-Version: 2.1
Name: mtenv
Version: 1.0
Summary: MTEnv: MultiTask Environments for Reinforcement Learning
Home-page: https://github.com/facbookresearch/mtenv
Author: Shagun Sodhani, Ludovic Denoyer, Pierre-Alexandre Kamienny, Olivier Delalleau
Author-email: sshagunsodhani@gmail.com, denoyer@fb.com, pakamienny@fb.com, odelalleau@fb.com
License: UNKNOWN
Platform: UNKNOWN
Classifier: Programming Language :: Python :: 3.6
Classifier: Programming Language :: Python :: 3.7
Classifier: Programming Language :: Python :: 3.8
Classifier: Programming Language :: Python :: 3.9
Classifier: License :: OSI Approved :: MIT License
Classifier: Operating System :: OS Independent
Requires-Python: >=3.6
Requires-Dist: gym (>=0.16.0)
Requires-Dist: numpy (>=1.10.4<1.20)
